scrapetube/__init__.py
scrapetube/scrapetube.py
scrapetube-2.5.0.dist-info/LICENSE
scrapetube-2.5.0.dist-info/METADATA
scrapetube-2.5.0.dist-info/WHEEL
scrapetube-2.5.0.dist-info/top_level.txt
scrapetube-2.5.0.dist-info/RECORD
