Metadata-Version: 2.1
Name: scrapetube
Version: 2.5.0
Summary: Scrape youtube without the official youtube api and without selenium.
Home-page: https://github.com/dermasmid/scrapetube
Author: Cheskel Twersky
Author-email: twerskycheskel@gmail.com
License: MIT
Project-URL: Documentation, https://scrapetube.readthedocs.io/en/latest/
Keywords: youtube python channel videos search playlist list get
Platform: UNKNOWN
Classifier: Programming Language :: Python :: 3
Classifier: License :: OSI Approved :: MIT License
Classifier: Operating System :: OS Independent
Requires-Python: >=3.6
License-File: LICENSE
Requires-Dist: requests
Requires-Dist: typing-extensions
